eigendaten/__init__.py
eigendaten/eigendata.py
eigendaten/exceptions.py
eigendaten/schemas.py
eigendaten-0.1.5.dist-info/LICENSE
eigendaten-0.1.5.dist-info/METADATA
eigendaten-0.1.5.dist-info/WHEEL
eigendaten-0.1.5.dist-info/RECORD
